demo_energy_consumption/__init__.py
demo_energy_consumption/cli.py
demo_energy_consumption/demo_energy_consumption.py
demo_energy_consumption/query_execution.py
demo_energy_consumption-0.2.3.dist-info/AUTHORS.rst
demo_energy_consumption-0.2.3.dist-info/LICENSE
demo_energy_consumption-0.2.3.dist-info/METADATA
demo_energy_consumption-0.2.3.dist-info/WHEEL
demo_energy_consumption-0.2.3.dist-info/entry_points.txt
demo_energy_consumption-0.2.3.dist-info/top_level.txt
demo_energy_consumption-0.2.3.dist-info/RECORD
