Metadata-Version: 2.1
Name: demo-energy-consumption
Version: 0.2.3
Summary: demo energy consumption shows how to seamlessly leverage Teradata Vantage in your Python projects.
Home-page: https://github.com/denismolin/demo_energy_consumption
Author: Denis Molin
Author-email: denis.molin@teradata.com
License: MIT license
Keywords: demo_energy_consumption
Platform: UNKNOWN
Classifier: Development Status :: 2 - Pre-Alpha
Classifier: Intended Audience :: Developers
Classifier: License :: OSI Approved :: MIT License
Classifier: Natural Language :: English
Classifier: Programming Language :: Python :: 3
Classifier: Programming Language :: Python :: 3.6
Classifier: Programming Language :: Python :: 3.7
Classifier: Programming Language :: Python :: 3.8
Requires-Python: >=3.6
Requires-Dist: Click (>=7.0)
Requires-Dist: docker (>=5)
Requires-Dist: greenlet (>=1)
Requires-Dist: pycryptodome (>=3)
Requires-Dist: sqlalchemy (>=1.4)
Requires-Dist: teradataml (>=17)
Requires-Dist: teradatasql (>=17)
Requires-Dist: teradatasqlalchemy (>=17)
Requires-Dist: websocket-client (>=1.2)
